BioSQL/__init__.py
BioSQL/BioSeqDatabase.py
BioSQL/DBUtils.py
BioSQL/py.typed
BioSQL/BioSeq.py
BioSQL/Loader.py
Bio/MaxEntropy.py
Bio/pairwise2.py
Bio/bgzf.py
Bio/kNN.py
Bio/LogisticRegression.py
Bio/SeqRecord.py
Bio/Seq.py
Bio/cpairwise2module.c
Bio/__init__.py
Bio/SeqFeature.py
Bio/File.py
Bio/MarkovModel.py
Bio/_utils.py
Bio/NaiveBayes.py
Bio/py.typed
Bio/cpairwise2.cpython-310-aarch64-linux-gnu.so
Bio/Pathway/__init__.py
Bio/Pathway/Rep/Graph.py
Bio/Pathway/Rep/MultiGraph.py
Bio/Pathway/Rep/__init__.py
Bio/Alphabet/__init__.py
Bio/AlignIO/MafIO.py
Bio/AlignIO/EmbossIO.py
Bio/AlignIO/PhylipIO.py
Bio/AlignIO/NexusIO.py
Bio/AlignIO/FastaIO.py
Bio/AlignIO/__init__.py
Bio/AlignIO/ClustalIO.py
Bio/AlignIO/MsfIO.py
Bio/AlignIO/Interfaces.py
Bio/AlignIO/StockholmIO.py
Bio/AlignIO/MauveIO.py
Bio/phenotype/phen_micro.py
Bio/phenotype/__init__.py
Bio/phenotype/pm_fitting.py
Bio/Restriction/Restriction_Dictionary.py
Bio/Restriction/__init__.py
Bio/Restriction/PrintFormat.py
Bio/Restriction/Restriction.py
Bio/Compass/__init__.py
Bio/Data/IUPACData.py
Bio/Data/PDBData.py
Bio/Data/CodonTable.py
Bio/Data/__init__.py
Bio/Align/fasta.py
Bio/Align/sam.py
Bio/Align/tabular.py
Bio/Align/bigbed.py
Bio/Align/bigpsl.py
Bio/Align/interfaces.py
Bio/Align/analysis.py
Bio/Align/hhr.py
Bio/Align/clustal.py
Bio/Align/maf.py
Bio/Align/chain.py
Bio/Align/nexus.py
Bio/Align/_codonaligner.cpython-310-aarch64-linux-gnu.so
Bio/Align/msf.py
Bio/Align/exonerate.py
Bio/Align/_aligncore.cpython-310-aarch64-linux-gnu.so
Bio/Align/__init__.py
Bio/Align/a2m.py
Bio/Align/_aligncore.c
Bio/Align/stockholm.py
Bio/Align/bigmaf.py
Bio/Align/AlignInfo.py
Bio/Align/phylip.py
Bio/Align/emboss.py
Bio/Align/_codonaligner.c
Bio/Align/bed.py
Bio/Align/psl.py
Bio/Align/mauve.py
Bio/Align/_pairwisealigner.cpython-310-aarch64-linux-gnu.so
Bio/Align/_pairwisealigner.c
Bio/Align/substitution_matrices/__init__.py
biopython-1.84.dist-info/RECORD
biopython-1.84.dist-info/METADATA
biopython-1.84.dist-info/WHEEL
biopython-1.84.dist-info/top_level.txt
biopython-1.84.dist-info/LICENSE.rst
biopython-1.84.dist-info/LICENSE
